{
    "devices.5.data.lastSend": {
      "value": 123766,
      "type": "int",
      "invalidateTime": 1413873807,
      "updateTime": 1413875079
    },
    "devices.5.data.lastReceived": {
      "value": 0,
      "type": "int",
      "invalidateTime": 1412757539,
      "updateTime": 1413875080
    },
    "devices.5.instances.0.commandClasses.50.data.0": {
      "value": null,
      "type": "empty",
      "sensorType": {
        "value": 1,
        "type": "int",
        "invalidateTime": 1413186348,
        "updateTime": 1413186349
      },
      "sensorTypeString": {
        "value": "Electric ",
        "type": "string",
        "invalidateTime": 1413186348,
        "updateTime": 1413186349
      },
      "val": {
        "value": 0.267,
        "type": "float",
        "invalidateTime": 1413186348,
        "updateTime": 1413875080
      },
      "scale": {
        "value": 0,
        "type": "int",
        "invalidateTime": 1413186348,
        "updateTime": 1413186349
      },
      "scaleString": {
        "value": "kWh",
        "type": "string",
        "invalidateTime": 1413186348,
        "updateTime": 1413186349
      },
      "ratetype": {
        "value": 1,
        "type": "int",
        "invalidateTime": 1413186348,
        "updateTime": 1413875080
      },
      "delta": {
        "value": 1,
        "type": "int",
        "invalidateTime": 1413186348,
        "updateTime": 1413875080
      },
      "previous": {
        "value": 0.267,
        "type": "float",
        "invalidateTime": 1413186348,
        "updateTime": 1413875080
      },
      "invalidateTime": 1413875078,
      "updateTime": 1413875080
    },
    "devices.5.instances.0.commandClasses.50.data.2": {
      "value": null,
      "type": "empty",
      "sensorType": {
        "value": 1,
        "type": "int",
        "invalidateTime": 1413186348,
        "updateTime": 1413186349
      },
      "sensorTypeString": {
        "value": "Electric ",
        "type": "string",
        "invalidateTime": 1413186348,
        "updateTime": 1413186349
      },
      "val": {
        "value": 0.586,
        "type": "float",
        "invalidateTime": 1413186348,
        "updateTime": 1413875079
      },
      "scale": {
        "value": 2,
        "type": "int",
        "invalidateTime": 1413186348,
        "updateTime": 1413186349
      },
      "scaleString": {
        "value": "W",
        "type": "string",
        "invalidateTime": 1413186348,
        "updateTime": 1413186349
      },
      "ratetype": {
        "value": 1,
        "type": "int",
        "invalidateTime": 1413186348,
        "updateTime": 1413875079
      },
      "delta": {
        "value": 9,
        "type": "int",
        "invalidateTime": 1413186348,
        "updateTime": 1413875079
      },
      "previous": {
        "value": 0.267,
        "type": "float",
        "invalidateTime": 1413186348,
        "updateTime": 1413875079
      },
      "invalidateTime": 1413875078,
      "updateTime": 1413875079
    },
    "devices.31.instances.0.commandClasses.50.data.0": {
      "value": null,
      "type": "empty",
      "sensorType": {
        "value": null,
        "type": "empty",
        "invalidateTime": 1413808195,
        "updateTime": 1413808196
      },
      "sensorTypeString": {
        "value": null,
        "type": "empty",
        "invalidateTime": 1413808195,
        "updateTime": 1413808196
      },
      "val": {
        "value": null,
        "type": "empty",
        "invalidateTime": 1413808195,
        "updateTime": 1413808196
      },
      "scale": {
        "value": null,
        "type": "empty",
        "invalidateTime": 1413808195,
        "updateTime": 1413808196
      },
      "scaleString": {
        "value": null,
        "type": "empty",
        "invalidateTime": 1413808195,
        "updateTime": 1413808196
      },
      "invalidateTime": 1413875079,
      "updateTime": 1413808195
    },
  "updateTime": 1413875084
}